{"description": "This package installs all the components of JetBrains dotUltimate.\n\nThe dotUltimate license will cover all paid .NET & Visual Studio tools from JetBrains \n(ReSharper, ReSharper C++, Rider, dotTrace, dotMemory, and dotCover). \nIt will cost the same as ReSharper Ultimate currently does, but will also include Rider. \nHolders of active ReSharper Ultimate and ReSharper Ultimate+Rider licenses will be automatically transferred to the new dotUltimate, with all their continuity discounts preserved.\n\n### Package Specific\n\nBy default all components are installed. You can pass in parameters to de-select specific components.\n\n#### Package Parameters\n\nThe following package parameters can be set:\n\n * `/PerMachine` - install machine-wide (instead of per-user)\n * `/NoResharper` - don't install ReSharper\n * `/NoDotTrace` - don't install dotTrace\n * `/NoDotMemory` - don't install dotMemory\n * `/NoDotCover` - don't install dotCover\n * `/NoDotPeek` - don't install dotPeek\n * `/NoRider` - don't install Rider\n * `/NoCpp` - don't install ReSharper C++\n * `/NoTeamCityAddin` - don't install TeamCity Addin\n\nThese parameters can be passed to the installer with the use of `--params`.\nFor example: `--params \"'/NoCpp /NoTeamCityAddin'\"`.", "updated": "2024-03-23T14:48:29Z", "galleryUrl": "https://community.chocolatey.org/packages/dotUltimate/2023.3.4", "abuseUrl": "https://community.chocolatey.org/package/ReportAbuse/dotUltimate/2023.3.4", "licenseUrl": "https://www.jetbrains.com/resharper/buy/index.jsp?product=ultimate", "packageName": "dotUltimate", "displayName": "dotUltimate", "summary": "JetBrains dotUltimate", "version": "2023.3.4", "icon": "http://raw.githubusercontent.com/flcdrg/au-packages/master/dotUltimate/icons/logo.png", "author": "JetBrains", "downloadCount": 19957, "tags": ["ReSharper", "JetBrains", "dotCover", "dotMemory", "dotPeek", "dotTrace", "TeamCity", "C++", "Ultimate", "Rider", "admin"]}