{"description": "# Microsoft Report Viewer 2015 Runtime\n\n## Description\n\nThe Microsoft Report Viewer 2015 Runtime redistributable package, includes controls for viewing reports designed using Microsoft reporting technology.\n\n## Supported Operating System\n\nWindows 7, Windows 8, Windows 8.1, Windows Server 2003 Service Pack 2, Windows Server 2008 R2 SP1, Windows Server 2012, Windows Vista Service Pack 2\n\n## Pre-requisites\n\n* Microsoft SQL Server 2008 Reporting Services or higher for server processing mode.\n* NET Framework 3.5 SP1 or .NET Framework 4.0.\n* Check C:\\Windows\\Microsoft.NET\\Framework64\n* NET Framework 3.5 is there if we see a folder named v3.5. Further, use the registry to see whether SP1 for v3.5 is there [http://support.microsoft.com/kb/318785](http://support.microsoft.com/kb/318785)\n* HKEY_LOCAL_MACHINE\\SOFTWARE\\Microsoft\\NET Framework Setup\\NDP\\v3.5 needs to have DWORD named Install with value 1\n* If SP1 is not installed, it can be installed from the Microsoft .NET Framework 3.5 Service Pack 1\n* NET Framework 4.0 is there if we see a folder named v4.0\n* Microsoft SQL Server System CLR Types package\n* It is available in the Install Instructions section of the Microsoft\u00ae SQL Server\u00ae 2014 Feature Pack page.\n* Microsoft\u00ae System CLR Types for Microsoft\u00ae SQL Server\u00ae 2014\n* Ensure this order of setup\n* Ensure we have the required .NET Framework version per step 1a.\n* Run the SQL Server System CLR Types setup from step 1b.\n* Run the Report Viewer 2015 runtime setup\n\n## Features\n\n* Install and uninstall via Chocolatey\n* Requires source path to MyGet\n* Supports only 32-bit version\n\n## Changelog\n\n### 2017-04-15 Build 12.0.2402.15\n\n* initial build\n* version 12.0.2402.15\n* Virus Total Link - [https://www.virustotal.com/pl/file/85adfc54e0ede6a847d3cbfd8026330114a78923ef969cd0b4cb99cd28b0fec7/analysis/](https://www.virustotal.com/pl/file/85adfc54e0ede6a847d3cbfd8026330114a78923ef969cd0b4cb99cd28b0fec7/analysis/)\n\n## Usage\n\n### Direct\n\n```\n\nchoco install ms-reportviewer2015\n\n```\n\n### YAML (Foreman)\n\n```\n\nms-reportviewer2015:\n  ensure: latest\n  uninstall_options: \"--force --all-versions\"\n  provider: chocolatey\n\n```\n\nor\n\n```\n\nms-reportviewer2015:\n  ensure: latest\n\n```", "updated": "2024-03-24T01:18:29Z", "galleryUrl": "https://community.chocolatey.org/packages/ms-reportviewer2015/12.0.2402.15", "abuseUrl": "https://community.chocolatey.org/package/ReportAbuse/ms-reportviewer2015/12.0.2402.15", "licenseUrl": "https://www.microsoft.com/en-us/download/details.aspx?id=45496", "packageName": "ms-reportviewer2015", "displayName": "Microsoft Report Viewer 2015 Runtime", "summary": "The Microsoft Report Viewer 2015 Runtime redistributable package, includes controls for viewing reports designed using Microsoft reporting technology.", "version": "12.0.2402.15", "icon": "", "author": "Microsoft", "downloadCount": 24805, "tags": ["microsoft", "report", "viewer", "2015", "runtime", "admin"]}