{"description": "## Treecell - View spreadsheets as hierarchy\n\n![Screenshot of Treecell](https://www.japplis.com/treecell/images/treecell-screenshot.png)\n\nTreecell is a software that represents your data from Excel or CSV from a table to a navigatable tree. \n        You can expand and collapse same value to easily find data.\n        Rearrange the column orders and which columns to show or hide.\n        By default all is collapsed, so it's easier to show data only from a specific group and leave the other data confidential/hidden.\n        You can also show statistics on selected nodes.\n        Show the window always on top and translucent.\n        \n        Commercial: Free to try for one day.", "updated": "2024-03-20T11:33:25Z", "galleryUrl": "https://community.chocolatey.org/packages/treecell/1.1", "abuseUrl": "https://community.chocolatey.org/package/ReportAbuse/treecell/1.1", "licenseUrl": "https://www.japplis.com/treecell/license.txt", "packageName": "treecell", "displayName": "Treecell", "summary": "View spreadsheets as hierarchy", "version": "1.1", "icon": "https://www.japplis.com/treecell/images/Treecell256.png", "author": "Japplis", "downloadCount": 41, "tags": ["excel", "spreadsheet", "sheet", "tree", "hierarchy", "expand", "collapse", "pivot", "confidential"]}